lhe/__init__.py
lhe/lhe.py
lhe-0.9.0.dist-info/LICENSE
lhe-0.9.0.dist-info/METADATA
lhe-0.9.0.dist-info/WHEEL
lhe-0.9.0.dist-info/top_level.txt
lhe-0.9.0.dist-info/RECORD
