Metadata-Version: 2.1
Name: lhe
Version: 0.9.0
Summary: Leveled homomorphic encryption library supportingup to three multiplications and unlimited additions.
Home-page: https://github.com/nthparty/lhe
Author: Wyatt Howe
Author-email: wyatt@nthparty.com
License: MIT
License-File: LICENSE
Requires-Dist: mclbn256
Provides-Extra: coveralls
Requires-Dist: coveralls (~=3.3.1) ; extra == 'coveralls'
Provides-Extra: docs
Requires-Dist: sphinx (~=4.2.0) ; extra == 'docs'
Requires-Dist: sphinx-rtd-theme (~=1.0.0) ; extra == 'docs'
Provides-Extra: lint
Requires-Dist: pylint (~=2.14.0) ; extra == 'lint'
Provides-Extra: publish
Requires-Dist: setuptools (~=62.0) ; extra == 'publish'
Requires-Dist: wheel (~=0.37) ; extra == 'publish'
Requires-Dist: twine (~=4.0) ; extra == 'publish'
Provides-Extra: test
Requires-Dist: pytest (~=7.0) ; extra == 'test'
Requires-Dist: pytest-cov (~=3.0) ; extra == 'test'
